{
  "id": 1464,
  "slug": "locked-out-why-a-403-forbidden-error-on-wp-admin-could-be-a-malicious-htaccess-hack",
  "date": "2025-10-09T18:48:41",
  "modified": "2025-10-07T12:52:57",
  "title": "Locked Out? Why a 403 Forbidden Error on wp-admin Could Be a Malicious .htaccess Hack",
  "content": "<p>It’s a moment every website owner dreads. You go to log in to your WordPress dashboard by visiting <code>yoursite.com/wp-admin</code>, but instead of the familiar login screen, you’re hit with a stark, frustrating error: <strong>403 Forbidden</strong>. 🚫</p>\n<p>This error means your server understands your request, but it&#8217;s refusing to let you in. While there can be several causes, one of the most common and malicious reasons is a compromised <code>.htaccess</code> file placed by a hacker specifically to lock you out.</p>\n<p>This post will explain exactly how this attack works, why hackers do it, and how you can regain access to your site.</p>\n<hr />\n<h2>The Culprit: A Deceptively Simple Piece of Code</h2>\n<p>The attack often comes down to a small <code>.htaccess</code> file containing what looks like a security rule. A hacker will place a file with the following code inside your <code>/wp-admin/</code> directory:</p>\n<pre><code>&lt;FilesMatch '.(py|exe|php|PHP|Php|PHp|pHp|pHP|pHP7|PHP7|phP|PhP|php5|suspected)$'&gt;\r\nOrder allow,deny\r\nDeny from all\r\n&lt;/FilesMatch&gt;\r\n</code></pre>\n<p>At first glance, this might seem like a good thing. It’s blocking access to executable files, right? But the devil is in the details—and the location.</p>\n<h3>Why This Code Locks You Out</h3>\n<p>To understand the attack, you need to know two simple things:</p>\n<ol>\n<li>Your entire WordPress dashboard is run by a collection of <code>.php</code> files located in the <code>/wp-admin/</code> folder. The login page itself is powered by <code>wp-login.php</code>.</li>\n<li>The <code>.htaccess</code> file sets the rules for the folder it’s in and all the subfolders under it.</li>\n</ol>\n<p>The code snippet above tells the server: <strong>&#8220;For any file ending in .php (and its variations), deny access to everyone.&#8221;</strong></p>\n<p>When a hacker places this <code>.htaccess</code> file inside your <code>/wp-admin/</code> folder, they are setting a trap. The moment you try to access your login page, your browser asks the server for the <code>wp-login.php</code> file. The server checks the rules in the <code>/wp-admin/</code> folder, finds the malicious <code>.htaccess</code> file, sees the &#8220;Deny from all&#8221; rule for <code>.php</code> files, and immediately blocks the request.</p>\n<p>The result? A <strong>403 Forbidden</strong> error. The server is simply following the hacker&#8217;s malicious instructions.</p>\n<p><img loading=\"lazy\" decoding=\"async\" class=\" wp-image-1463 aligncenter\" src=\"https://cms.mdpabel.com/wp-content/uploads/2025/10/Screenshot_2-300x132.png\" alt=\"\" width=\"641\" height=\"282\" srcset=\"https://cms.mdpabel.com/wp-content/uploads/2025/10/Screenshot_2-300x132.png 300w, https://cms.mdpabel.com/wp-content/uploads/2025/10/Screenshot_2-1024x452.png 1024w, https://cms.mdpabel.com/wp-content/uploads/2025/10/Screenshot_2-768x339.png 768w, https://cms.mdpabel.com/wp-content/uploads/2025/10/Screenshot_2.png 1052w\" sizes=\"auto, (max-width: 641px) 100vw, 641px\" /></p>\n<h3>The Hacker&#8217;s Motive: Why Lock You Out?</h3>\n<p>Why would a hacker want to block you from your own site? It’s a strategic move that serves several purposes:</p>\n<ul>\n<li><strong>To Prevent Cleanup:</strong> By locking you out, the hacker prevents you from discovering and removing other malware, spam pages, or backdoors they&#8217;ve hidden on your site.</li>\n<li><strong>To Maintain Control:</strong> While you&#8217;re locked out, they have free reign. They can use your site to send spam emails, redirect your traffic, or attack other websites.</li>\n<li><strong>To Stop Updates:</strong> If you can&#8217;t log in, you can&#8217;t update your plugins, themes, or WordPress core. This keeps known security vulnerabilities open for the hacker to continue exploiting.</li>\n</ul>\n<p>It’s a digital deadbolt, designed to give the attacker time and control while leaving you helpless.</p>\n<hr />\n<h2>How to Fix the 403 Error and Regain Access</h2>\n<p>Since you can&#8217;t access your site through your browser, you&#8217;ll need to access your website&#8217;s files directly. You can do this using an <strong>FTP client</strong> (like FileZilla) or the <strong>File Manager</strong> in your hosting control panel (like cPanel or Plesk).</p>\n<h3>Step-by-Step Guide to Removing the Malware</h3>\n<ol>\n<li><strong>Connect to Your Server:</strong> Log in to your site’s files using your FTP or File Manager credentials.</li>\n<li><strong>Navigate to the <code>wp-admin</code> Folder:</strong> Go to the root directory of your WordPress installation (often <code>public_html</code> or <code>www</code>) and then open the <code>/wp-admin/</code> folder.</li>\n<li><strong>Find the Malicious <code>.htaccess</code> File:</strong> Look for an <code>.htaccess</code> file inside this folder. <strong>A default WordPress installation does not have an <code>.htaccess</code> file in the <code>/wp-admin/</code> directory.</strong> If you see one, it is almost certainly malware.</li>\n<li><strong>Delete the File:</strong> Right-click on the <code>.htaccess</code> file inside <code>/wp-admin/</code> and delete it. Be careful not to delete the main <code>.htaccess</code> file located in your root directory, as that one is necessary for your site to work. (Though you should check that one for malicious code as well!)</li>\n<li><strong>Try Logging In Again:</strong> Go back to your browser and try to access <code>yoursite.com/wp-admin</code>. You should now see the login screen.</li>\n</ol>\n<h3>Important: You&#8217;re Not Done Yet!</h3>\n<p>Regaining access is just the first step. Deleting the <code>.htaccess</code> file is like taking the deadbolt off the door, but the intruder is still inside your house. The hack that allowed them to place that file in the first place must be found and cleaned.</p>\n<p>After regaining access, you should immediately:</p>\n<ul>\n<li><strong>Run a Security Scan:</strong> Use a plugin like Wordfence or Sucuri to perform a deep scan of your entire website to find other malicious files or backdoors.</li>\n<li><strong>Change All Passwords:</strong> Immediately change your WordPress admin, FTP, hosting panel, and database passwords.</li>\n<li><strong>Check for Unknown Users:</strong> In your WordPress dashboard, go to &#8220;Users&#8221; and delete any admin accounts you don&#8217;t recognize.</li>\n<li><strong>Update Everything:</strong> Ensure your WordPress core, plugins, and themes are all updated to the latest versions to patch any security holes.</li>\n</ul>\n<hr />\n<h2>Conclusion</h2>\n<p>A 403 Forbidden error on your <code>wp-admin</code> page is an alarming experience, but it’s often fixable. By understanding that a single, maliciously placed <code>.htaccess</code> file can be the cause, you can take direct action to remove it and get back into your site. Just remember that regaining access is only half the battle—a full security cleanup is essential to truly secure your website for the long term.</p>\n",
  "excerpt": "<p>It’s a moment every website owner dreads. You go to log in to your WordPress dashboard by visiting yoursite.com/wp-admin, but instead of the familiar login screen, you’re hit with a stark, frustrating error: 403 Forbidden. 🚫 This error means your server understands your request, but it&#8217;s refusing to let you in. While there can be [&hellip;]</p>\n",
  "link": "https://cms.mdpabel.com/locked-out-why-a-403-forbidden-error-on-wp-admin-could-be-a-malicious-htaccess-hack/",
  "yoastHead": "<link rel=\"canonical\" href=\"https://www.mdpabel.com/blog/locked-out-why-a-403-forbidden-error-on-wp-admin-could-be-a-malicious-htaccess-hack/\" />\n<!-- This site is optimized with the Yoast SEO Premium plugin v25.9 (Yoast SEO v26.8) - https://yoast.com/product/yoast-seo-premium-wordpress/ -->\n<title>Locked Out? Why a 403 Forbidden Error on wp-admin Could Be a Malicious .htaccess Hack - MD Pabel</title>\n<meta name=\"robots\" content=\"index, follow, max-snippet:-1, max-image-preview:large, max-video-preview:-1\" />\n<meta property=\"og:locale\" content=\"en_US\" />\n<meta property=\"og:type\" content=\"article\" />\n<meta property=\"og:title\" content=\"Locked Out? Why a 403 Forbidden Error on wp-admin Could Be a Malicious .htaccess Hack\" />\n<meta property=\"og:description\" content=\"It’s a moment every website owner dreads. You go to log in to your WordPress dashboard by visiting yoursite.com/wp-admin, but instead of the familiar login screen, you’re hit with a stark, frustrating error: 403 Forbidden. 🚫 This error means your server understands your request, but it&#8217;s refusing to let you in. While there can be [&hellip;]\" />\n<meta property=\"og:url\" content=\"https://www.mdpabel.com/blog/locked-out-why-a-403-forbidden-error-on-wp-admin-could-be-a-malicious-htaccess-hack/\" />\n<meta property=\"og:site_name\" content=\"MD Pabel\" />\n<meta property=\"article:author\" content=\"https://www.mdpabel.com/author/mdpabel/\" />\n<meta property=\"article:published_time\" content=\"2025-10-09T12:48:41+00:00\" />\n<meta property=\"og:image\" content=\"https://cms.mdpabel.com/wp-content/uploads/2025/10/403-Forbidden-Error-on-wp-admin.png\" />\n\t<meta property=\"og:image:width\" content=\"1536\" />\n\t<meta property=\"og:image:height\" content=\"1024\" />\n\t<meta property=\"og:image:type\" content=\"image/png\" />\n<meta name=\"author\" content=\"MD Pabel\" />\n<meta name=\"twitter:card\" content=\"summary_large_image\" />\n<meta name=\"twitter:label1\" content=\"Written by\" />\n\t<meta name=\"twitter:data1\" content=\"MD Pabel\" />\n\t<meta name=\"twitter:label2\" content=\"Est. reading time\" />\n\t<meta name=\"twitter:data2\" content=\"5 minutes\" />\n<script type=\"application/ld+json\" class=\"yoast-schema-graph\">{\"@context\":\"https://schema.org\",\"@graph\":[{\"@type\":\"TechArticle\",\"@id\":\"https://www.mdpabel.com/blog/locked-out-why-a-403-forbidden-error-on-wp-admin-could-be-a-malicious-htaccess-hack/\",\"isPartOf\":{\"@id\":\"https://www.mdpabel.com/blog/locked-out-why-a-403-forbidden-error-on-wp-admin-could-be-a-malicious-htaccess-hack/\"},\"author\":{\"name\":\"MD Pabel\",\"@id\":\"https://www.mdpabel.com/#/schema/person/73e3797b5dc8d6434e9e35e1708bb0c4\"},\"headline\":\"Locked Out? Why a 403 Forbidden Error on wp-admin Could Be a Malicious .htaccess Hack\",\"datePublished\":\"2025-10-09T12:48:41+00:00\",\"mainEntityOfPage\":{\"@id\":\"https://www.mdpabel.com/blog/locked-out-why-a-403-forbidden-error-on-wp-admin-could-be-a-malicious-htaccess-hack/\"},\"wordCount\":843,\"commentCount\":0,\"image\":{\"@id\":\"https://www.mdpabel.com/blog/locked-out-why-a-403-forbidden-error-on-wp-admin-could-be-a-malicious-htaccess-hack/\"},\"thumbnailUrl\":\"https://cms.mdpabel.com/wp-content/uploads/2025/10/403-Forbidden-Error-on-wp-admin.png?wsr\",\"inLanguage\":\"en-US\",\"potentialAction\":[{\"@type\":\"CommentAction\",\"name\":\"Comment\",\"target\":[\"https://www.mdpabel.com/blog/locked-out-why-a-403-forbidden-error-on-wp-admin-could-be-a-malicious-htaccess-hack/\"]}]},{\"@type\":\"WebPage\",\"@id\":\"https://www.mdpabel.com/blog/locked-out-why-a-403-forbidden-error-on-wp-admin-could-be-a-malicious-htaccess-hack/\",\"url\":\"https://www.mdpabel.com/blog/locked-out-why-a-403-forbidden-error-on-wp-admin-could-be-a-malicious-htaccess-hack/\",\"name\":\"Locked Out? Why a 403 Forbidden Error on wp-admin Could Be a Malicious .htaccess Hack - MD Pabel\",\"isPartOf\":{\"@id\":\"https://www.mdpabel.com/#website\"},\"primaryImageOfPage\":{\"@id\":\"https://www.mdpabel.com/blog/locked-out-why-a-403-forbidden-error-on-wp-admin-could-be-a-malicious-htaccess-hack/\"},\"image\":{\"@id\":\"https://www.mdpabel.com/blog/locked-out-why-a-403-forbidden-error-on-wp-admin-could-be-a-malicious-htaccess-hack/\"},\"thumbnailUrl\":\"https://cms.mdpabel.com/wp-content/uploads/2025/10/403-Forbidden-Error-on-wp-admin.png?wsr\",\"datePublished\":\"2025-10-09T12:48:41+00:00\",\"author\":{\"@id\":\"https://www.mdpabel.com/#/schema/person/73e3797b5dc8d6434e9e35e1708bb0c4\"},\"breadcrumb\":{\"@id\":\"https://www.mdpabel.com/blog/locked-out-why-a-403-forbidden-error-on-wp-admin-could-be-a-malicious-htaccess-hack/\"},\"inLanguage\":\"en-US\",\"potentialAction\":[{\"@type\":\"ReadAction\",\"target\":[\"https://www.mdpabel.com/blog/locked-out-why-a-403-forbidden-error-on-wp-admin-could-be-a-malicious-htaccess-hack/\"]}]},{\"@type\":\"ImageObject\",\"inLanguage\":\"en-US\",\"@id\":\"https://www.mdpabel.com/blog/locked-out-why-a-403-forbidden-error-on-wp-admin-could-be-a-malicious-htaccess-hack/\",\"url\":\"https://cms.mdpabel.com/wp-content/uploads/2025/10/403-Forbidden-Error-on-wp-admin.png?wsr\",\"contentUrl\":\"https://cms.mdpabel.com/wp-content/uploads/2025/10/403-Forbidden-Error-on-wp-admin.png?wsr\",\"width\":1536,\"height\":1024},{\"@type\":\"BreadcrumbList\",\"@id\":\"https://www.mdpabel.com/blog/locked-out-why-a-403-forbidden-error-on-wp-admin-could-be-a-malicious-htaccess-hack/\",\"itemListElement\":[{\"@type\":\"ListItem\",\"position\":1,\"name\":\"Home\",\"item\":\"https://www.mdpabel.com/\"},{\"@type\":\"ListItem\",\"position\":2,\"name\":\"Locked Out? Why a 403 Forbidden Error on wp-admin Could Be a Malicious .htaccess Hack\"}]},{\"@type\":\"WebSite\",\"@id\":\"https://www.mdpabel.com/#website\",\"url\":\"https://www.mdpabel.com/\",\"name\":\"MD Pabel\",\"description\":\"Full Stack Developer, Malware Removal &amp; Security Specialist\",\"potentialAction\":[{\"@type\":\"SearchAction\",\"target\":{\"@type\":\"EntryPoint\",\"urlTemplate\":\"https://www.mdpabel.com/blog/?s={search_term_string}\"},\"query-input\":{\"@type\":\"PropertyValueSpecification\",\"valueRequired\":true,\"valueName\":\"search_term_string\"}}],\"inLanguage\":\"en-US\"},{\"@type\":\"Person\",\"@id\":\"https://www.mdpabel.com/#/schema/person/73e3797b5dc8d6434e9e35e1708bb0c4\",\"name\":\"MD Pabel\",\"image\":{\"@type\":\"ImageObject\",\"inLanguage\":\"en-US\",\"@id\":\"https://www.mdpabel.com/#/schema/person/image/\",\"url\":\"https://secure.gravatar.com/avatar/b6b48a60efe9dc8cd04d4a7e5c9b22cafd47332f65a407ce270e8ad7f8843372?s=96&d=mm&r=g\",\"contentUrl\":\"https://secure.gravatar.com/avatar/b6b48a60efe9dc8cd04d4a7e5c9b22cafd47332f65a407ce270e8ad7f8843372?s=96&d=mm&r=g\",\"caption\":\"MD Pabel\"},\"description\":\"MD Pabel is the Founder and CEO of 3Zero Digital, a leading agency specializing in custom web development, WordPress security, and malware removal. With over 7+ Years of experience, he has completed more than3200+ projects, served over 2300+ clients, and resolved4500+ cases of malware and hacked websites.\",\"sameAs\":[\"https://www.mdpabel.com/\",\"https://www.facebook.com/in/mdpabe1\",\"https://www.linkedin.com/in/mdpabe1\"],\"url\":\"https://www.mdpabel.com/author/mdpabel/\"}]}</script>\n<!-- / Yoast SEO Premium plugin. -->",
  "featuredImage": {
    "url": "https://cms.mdpabel.com/wp-content/uploads/2025/10/403-Forbidden-Error-on-wp-admin.png",
    "alt": ""
  },
  "categories": [
    {
      "id": 1,
      "name": "Uncategorized",
      "slug": "uncategorized"
    }
  ],
  "acf": {
    "custom_schema": ""
  }
}